endermite/__init__.py
endermite/__main__.py
endermite/component.py
endermite/component_method.py
endermite/decorators.py
endermite/error.py
endermite/function.py
endermite/mixins.py
endermite/project.py
endermite/resource.py
endermite/utils.py
endermite/cli/__init__.py
endermite/cli/build.py
endermite/cli/config.py
endermite/cli/init.py
endermite/cli/main.py
endermite/cli/utils.py
endermite/cli/watch.py
endermite/command/__init__.py
endermite/command/basic.py
endermite/command/mixin.py
endermite-0.0.7.dist-info/METADATA
endermite-0.0.7.dist-info/RECORD
endermite-0.0.7.dist-info/WHEEL
endermite-0.0.7.dist-info/entry_points.txt
endermite-0.0.7.dist-info/top_level.txt
tests/__init__.py
tests/test_cli.py
tests/test_endermite.py
tests/files/__init__.py
