Metadata-Version: 2.1
Name: endermite
Version: 0.0.7
Summary: A high-level, opinionated python framework for building Minecraft data packs
Home-page: https://github.com/vberlier/endermite
Author: Valentin Berlier
Author-email: berlier.v@gmail.com
License: MIT
Keywords: minecraft datapack python framework mcfunction map-making
Platform: any
Classifier: Development Status :: 1 - Planning
Classifier: License :: OSI Approved :: MIT License
Classifier: Programming Language :: Python :: 3.7
Requires-Python: >=3.7
Requires-Dist: click (==6.7)
Requires-Dist: nbtlib (==1.2.0)
Requires-Dist: mcpack (==0.3.0)
